bertrend/BERTopicModel.py
bertrend/BERTrend.py
bertrend/__init__.py
bertrend/article_scoring/__init__.py
bertrend/article_scoring/article_scoring.py
bertrend/article_scoring/prompts.py
bertrend/article_scoring/scoring_agent.py
bertrend/config/bertopic_default_config.toml
bertrend/config/bertrend_default_config.toml
bertrend/config/parameters.py
bertrend/config/services_default_config.toml
bertrend/demos/__init__.py
bertrend/demos/demos_utils/__init__.py
bertrend/demos/demos_utils/data_loading_component.py
bertrend/demos/demos_utils/embed_documents_component.py
bertrend/demos/demos_utils/i18n.py
bertrend/demos/demos_utils/i18n_translations.py
bertrend/demos/demos_utils/icons.py
bertrend/demos/demos_utils/parameters_component.py
bertrend/demos/demos_utils/state_utils.py
bertrend/demos/start_summarizer_app.sh
bertrend/demos/start_topic_analysis_app.sh
bertrend/demos/start_weak_signals_app.sh
bertrend/demos/streamlit_components/__init__.py
bertrend/demos/streamlit_components/clickable_df_component.py
bertrend/demos/streamlit_components/input_with_pills_component.py
bertrend/demos/summarization/__init__.py
bertrend/demos/summarization/summarizer_app.py
bertrend/demos/topic_analysis/.streamlit/config.toml
bertrend/demos/topic_analysis/__init__.py
bertrend/demos/topic_analysis/app.py
bertrend/demos/topic_analysis/app_utils.py
bertrend/demos/topic_analysis/demo_pages/__init__.py
bertrend/demos/topic_analysis/demo_pages/explore_topics.py
bertrend/demos/topic_analysis/demo_pages/newsletters_generation.py
bertrend/demos/topic_analysis/demo_pages/temporal_visualizations.py
bertrend/demos/topic_analysis/demo_pages/topic_visualizations.py
bertrend/demos/topic_analysis/demo_pages/training_page.py
bertrend/demos/topic_analysis/i18n_translations.py
bertrend/demos/weak_signals/.streamlit/config.toml
bertrend/demos/weak_signals/__init__.py
bertrend/demos/weak_signals/app.py
bertrend/demos/weak_signals/i18n_translations.py
bertrend/demos/weak_signals/visualizations_utils.py
bertrend-0.3.22.dist-info/METADATA
bertrend-0.3.22.dist-info/WHEEL
bertrend-0.3.22.dist-info/licenses/AUTHORS.txt
bertrend-0.3.22.dist-info/licenses/LICENSE.md
bertrend-0.3.22.dist-info/RECORD
