Metadata-Version: 2.4
Name: bertrend
Version: 0.3.22
Summary: BERTrend analyses topic evolution over time using state-of-the-art transformer models: topic modelling and LLM
License: LICENSE.md
License-File: AUTHORS.txt
License-File: LICENSE.md
Keywords: topics,BERTopic,transformers,weak signals,LLM,trend analysis
Author: Jérôme Picault
Author-email: jerome.picault@rte-france.com
Maintainer: Jérôme Picault
Maintainer-email: jerome.picault@rte-france.com
Requires-Python: >=3.12,<4.0
Classifier: Topic :: Scientific/Engineering :: Artificial Intelligence
Provides-Extra: apps
Requires-Dist: APScheduler (>=3.11.0)
Requires-Dist: PyJWT (>=2.10.1)
Requires-Dist: Pyqtree (==1.0.0)
Requires-Dist: SQLAlchemy (>=2.0.40)
Requires-Dist: arxiv (>=2.2.0) ; extra == "apps"
Requires-Dist: bertopic (==0.16.2)
Requires-Dist: black (>=24.10.0)
Requires-Dist: coverage (>=7.6.9)
Requires-Dist: cron-descriptor (>=1.4.5)
Requires-Dist: dask (==2024.12.0)
Requires-Dist: datamapplot (==0.3.0)
Requires-Dist: dateparser (>=1.2.0)
Requires-Dist: dill (>=0.4.0)
Requires-Dist: fastapi (>=0.120.0)
Requires-Dist: feedparser (>=6.0.11) ; extra == "apps"
Requires-Dist: gensim (>=4.3.3)
Requires-Dist: google-api-python-client (>=2.148.0) ; extra == "apps"
Requires-Dist: google-auth-oauthlib (>=1.2.1) ; extra == "apps"
Requires-Dist: googlenewsdecoder (>=0.1.7) ; extra == "apps"
Requires-Dist: goose3 (>=3.1.19) ; extra == "apps"
Requires-Dist: hdbscan (>=0.8.40)
Requires-Dist: ipython (>=8.28.0)
Requires-Dist: joblib (>=1.4.2)
Requires-Dist: jsonlines (>=4.0.0)
Requires-Dist: langchain-core (>=0.3.59)
Requires-Dist: langdetect (>=1.0.9)
Requires-Dist: loguru (>=0.7.3)
Requires-Dist: lxml-html-clean (>=0.2.2)
Requires-Dist: markdown (>=3.7)
Requires-Dist: newscatcherapi (>=0.7.3) ; extra == "apps"
Requires-Dist: newspaper4k (>=0.9.3.1) ; extra == "apps"
Requires-Dist: nltk (>=3.9.1)
Requires-Dist: numpy (<2)
Requires-Dist: openai (>=1.77.0)
Requires-Dist: openai-agents[litellm] (>=0.4.0)
Requires-Dist: openpyxl (>=3.1.5)
Requires-Dist: opentelemetry-exporter-otlp-proto-grpc (==1.25.0)
Requires-Dist: pandas (>=2.2.2)
Requires-Dist: plotly (>=5.24.1)
Requires-Dist: plotly-resampler (>=0.10.0)
Requires-Dist: pyarrow (>=21.0.0)
Requires-Dist: pygooglenews (>=0.1.3) ; extra == "apps"
Requires-Dist: pylabeladjust (==0.1.13)
Requires-Dist: pytest (>=8.4.0)
Requires-Dist: pytest-asyncio
Requires-Dist: python-dotenv (>=1.1.1)
Requires-Dist: requests (>=2.32.3)
Requires-Dist: scikit-learn (>=1.5.2)
Requires-Dist: scipy (==1.12)
Requires-Dist: seaborn (>=0.13.2)
Requires-Dist: sentence-transformers (==3.0.1)
Requires-Dist: sentencepiece (>=0.2.0)
Requires-Dist: starlette (>=0.46.2)
Requires-Dist: streamlit (>=1.50)
Requires-Dist: streamlit-code-editor (>=0.1.22)
Requires-Dist: supervisor (>=4.3.0)
Requires-Dist: thefuzz (>=0.22.1)
Requires-Dist: tiktoken (>=0.8.0)
Requires-Dist: tldextract (>=2.0.1)
Requires-Dist: tokenizers (<0.20.0)
Requires-Dist: torch (>=2.7.0)
Requires-Dist: tqdm (>=4.67.1)
Requires-Dist: typer (>=0.16.0)
Requires-Dist: umap-learn (>=0.5.7)
Project-URL: Bug Tracker, https://github.com/rte-france/BERTrend/issues
Project-URL: Documentation, https://github.com/rte-france/BERTrend
Project-URL: Homepage, https://github.com/rte-france/BERTrend
Project-URL: Repository, https://github.com/rte-france/BERTrend
